tairClient/__init__.py
tairClient/client.py
tairClient-0.1.3.dist-info/LICENSE
tairClient-0.1.3.dist-info/METADATA
tairClient-0.1.3.dist-info/WHEEL
tairClient-0.1.3.dist-info/top_level.txt
tairClient-0.1.3.dist-info/RECORD
